ai_git_commit/__init__.py
ai_git_commit/config.py
ai_git_commit/git.py
ai_git_commit/openai.py
ai_git_commit/prompts.py
ai_git_commit-0.1.5.dist-info/LICENSE.md
ai_git_commit-0.1.5.dist-info/METADATA
ai_git_commit-0.1.5.dist-info/WHEEL
ai_git_commit-0.1.5.dist-info/entry_points.txt
ai_git_commit-0.1.5.dist-info/RECORD
